{"_type":"export","__export_format":4,"__export_date":"2024-10-20T14:51:07.760Z","__export_source":"insomnia.desktop.app:v10.0.0","resources":[{"_id":"req_3f4ce6dac5d54d8c97a238861ec32e1f","parentId":"fld_befb2e56acdd4db9856c10fa00855b56","modified":1729119380377,"created":1729112141377,"url":"{{ _.base_url }}/product/20","name":"New Request","description":"","method":"DELETE","body":{},"parameters":[],"headers":[{"name":"User-Agent","value":"insomnia/10.0.0"}],"authentication":{"type":"bearer","token":"{{ _.token }}"},"metaSortKey":-1729112141377,"isPrivate":false,"pathParameters":[],"settingStoreCookies":true,"settingSendCookies":true,"settingDisableRenderRequestBody":false,"settingEncodeUrl":true,"settingRebuildPath":true,"settingFollowRedirects":"global","_type":"request"},{"_id":"fld_befb2e56acdd4db9856c10fa00855b56","parentId":"wrk_1ab8149399c840b69bb18c2b0d8ebd99","modified":1729090758366,"created":1729090758366,"name":"Product","description":"","environment":{},"environmentPropertyOrder":null,"metaSortKey":-1729090758366,"_type":"request_group"},{"_id":"wrk_1ab8149399c840b69bb18c2b0d8ebd99","parentId":null,"modified":1729089313631,"created":1729089313631,"name":"ManagementProductsAndUsers","description":"","scope":"collection","_type":"workspace"},{"_id":"req_b7e649b58bff49de9d3f458ef04f93ac","parentId":"fld_befb2e56acdd4db9856c10fa00855b56","modified":1729119831235,"created":1729089313636,"url":"{{ _.base_url }}/product/create","name":"Upload Product","description":"","method":"POST","body":{"mimeType":"application/json","text":"{\n\t\"name\": \"Rog Phone 6\",\n  \"description\": \"Celular gamer\",\n  \"price\": 1999.60,\n\t\"qty\": 10\n}"},"parameters":[],"headers":[{"name":"Content-Type","value":"application/json"},{"name":"User-Agent","value":"insomnia/9.3.3"}],"authentication":{"type":"bearer","token":"{{ _.token }}"},"metaSortKey":-1729090772619,"isPrivate":false,"pathParameters":[],"settingStoreCookies":true,"settingSendCookies":true,"settingDisableRenderRequestBody":false,"settingEncodeUrl":true,"settingRebuildPath":true,"settingFollowRedirects":"global","_type":"request"},{"_id":"req_007b0672594a4d64a973edf4a2d1e1ee","parentId":"fld_befb2e56acdd4db9856c10fa00855b56","modified":1729205019307,"created":1729112483919,"url":"{{ _.base_url }}/product/22","name":"Update Product","description":"","method":"PATCH","body":{"mimeType":"application/json","text":"{\n\t\"qty\": 11,\n\t\"createdAt\":\"2024-10-18T00:11:33.957Z\"\n}"},"parameters":[],"headers":[{"name":"Content-Type","value":"application/json"},{"name":"User-Agent","value":"insomnia/9.3.3"}],"authentication":{"type":"bearer","token":"{{ _.token }}"},"metaSortKey":-1729090772519,"isPrivate":false,"pathParameters":[],"settingStoreCookies":true,"settingSendCookies":true,"settingDisableRenderRequestBody":false,"settingEncodeUrl":true,"settingRebuildPath":true,"settingFollowRedirects":"global","_type":"request"},{"_id":"req_21bc8389de224a2eaf635ede38b14328","parentId":"fld_befb2e56acdd4db9856c10fa00855b56","modified":1729435832009,"created":1729089313637,"url":"{{ _.base_url }}/product/list","name":"List Products","description":"","method":"GET","body":{},"parameters":[{"id":"pair_1712f2bf9f1f487c84a13cad57fc814d","name":"order","value":"asc","description":"","disabled":true},{"id":"pair_8695e372934c40b194cf43fef3b5ef02","name":"dataOrder","value":"asc","description":"","disabled":false}],"headers":[{"name":"User-Agent","value":"insomnia/9.3.3","id":"pair_f1358d13bc7843558cf4bfbbacaa783e"}],"authentication":{"type":"bearer","token":"{{ _.token }}"},"metaSortKey":-1729090772419,"isPrivate":false,"pathParameters":[],"settingStoreCookies":true,"settingSendCookies":true,"settingDisableRenderRequestBody":false,"settingEncodeUrl":true,"settingRebuildPath":true,"settingFollowRedirects":"global","_type":"request"},{"_id":"req_1ac6ed63a01f414f8edb4df28e1514bb","parentId":"fld_f5c1c4bd68574867b7eb11aacce78d3d","modified":1729430115190,"created":1729089426468,"url":"{{ _.base_url }}/user/create","name":"Create User","description":"","method":"POST","body":{"mimeType":"application/json","text":"{\n\t\t\"cpf\": \"01756431202\",\n\t\t\"password\": \"12345678\",\n\t\t\"name\": \"Eduardo Baranowski\",\n\t\t\"username\": \"edu_baranowski\",\n\t\t\"password\": \"12345678\"\n}"},"parameters":[],"headers":[{"name":"Content-Type","value":"application/json"},{"name":"User-Agent","value":"insomnia/9.3.3"}],"authentication":{},"metaSortKey":-1729089431203,"isPrivate":false,"pathParameters":[],"settingStoreCookies":true,"settingSendCookies":true,"settingDisableRenderRequestBody":false,"settingEncodeUrl":true,"settingRebuildPath":true,"settingFollowRedirects":"global","_type":"request"},{"_id":"fld_f5c1c4bd68574867b7eb11aacce78d3d","parentId":"wrk_1ab8149399c840b69bb18c2b0d8ebd99","modified":1729089417148,"created":1729089417148,"name":"User","description":"","environment":{},"environmentPropertyOrder":null,"metaSortKey":-1729089417148,"_type":"request_group"},{"_id":"req_cc55a49402da408aa1e3eb74f3d34931","parentId":"fld_f5c1c4bd68574867b7eb11aacce78d3d","modified":1729380825759,"created":1729380630831,"url":"{{ _.base_url }}/user/40","name":"Update User","description":"","method":"PATCH","body":{"mimeType":"application/json","text":"{\n\t\"name\": \"Eduardo Baranowski\"\n}"},"parameters":[],"headers":[{"name":"Content-Type","value":"application/json"},{"name":"User-Agent","value":"insomnia/9.3.3"}],"authentication":{"type":"bearer","token":"{{ _.token }}"},"metaSortKey":-1729066859383,"isPrivate":false,"pathParameters":[],"settingStoreCookies":true,"settingSendCookies":true,"settingDisableRenderRequestBody":false,"settingEncodeUrl":true,"settingRebuildPath":true,"settingFollowRedirects":"global","_type":"request"},{"_id":"req_b578ff635dbc47a98fc4632ca943f333","parentId":"fld_f5c1c4bd68574867b7eb11aacce78d3d","modified":1729435184983,"created":1729340268074,"url":"{{ _.base_url }}/user/uploadImage/1","name":"Upload Image","description":"","method":"POST","body":{"mimeType":"multipart/form-data","params":[{"id":"pair_250b78b1be5847d092dc101035b5160e","name":"file","value":"","description":"","disabled":false,"type":"file","fileName":"/home/ebaranowski/Downloads/logo.png"}]},"parameters":[],"headers":[{"name":"Content-Type","value":"multipart/form-data"},{"name":"User-Agent","value":"insomnia/9.3.3"}],"authentication":{"type":"bearer","token":"","disabled":true},"metaSortKey":-1729044287563,"isPrivate":false,"pathParameters":[],"settingStoreCookies":true,"settingSendCookies":true,"settingDisableRenderRequestBody":false,"settingEncodeUrl":true,"settingRebuildPath":true,"settingFollowRedirects":"global","_type":"request"},{"_id":"req_80d51eed0a934d08a672b8c5ef7693d8","parentId":"fld_440d1f2207ce4c17b0208f6f63be5fec","modified":1729428965866,"created":1729090794042,"url":"{{ _.base_url }}/auth","name":"Login","description":"","method":"POST","body":{"mimeType":"application/json","text":"{\n\t\"cpf\": \"admin-master\",\n\t\"password\": \"123456789@\"\n}"},"parameters":[],"headers":[{"name":"Content-Type","value":"application/json"},{"name":"User-Agent","value":"insomnia/9.3.3"}],"authentication":{"type":"bearer","token":"","disabled":true},"metaSortKey":-1729089431203,"isPrivate":false,"pathParameters":[],"settingStoreCookies":true,"settingSendCookies":true,"settingDisableRenderRequestBody":false,"settingEncodeUrl":true,"settingRebuildPath":true,"settingFollowRedirects":"global","_type":"request"},{"_id":"fld_440d1f2207ce4c17b0208f6f63be5fec","parentId":"wrk_1ab8149399c840b69bb18c2b0d8ebd99","modified":1729090794041,"created":1729090794041,"name":"Auth","description":"","environment":{},"environmentPropertyOrder":null,"metaSortKey":-1725210364172,"_type":"request_group"},{"_id":"env_cfa4a851e76a4775a57f5dbb4aec6df7","parentId":"wrk_1ab8149399c840b69bb18c2b0d8ebd99","modified":1729431393020,"created":1729089313633,"name":"Base Environment","data":{"base_url":"http://localhost:3333","token":"eyJhbGciOiJIUzI1NiIsInR5cCI6IkpXVCJ9.eyJ1c2VybmFtZSI6ImFkbWluLW1hc3RlciIsInN1YiI6MSwiaWF0IjoxNzI5NDI5NTI2LCJleHAiOjE3Mjk1MTU5MjZ9.TzrgLBjmdU2yZ4KllQEsGLbSIQdkSq_LF7-hlHmyS90"},"dataPropertyOrder":{"&":["base_url","token"]},"color":null,"isPrivate":false,"metaSortKey":1724786055892,"_type":"environment"},{"_id":"jar_d63b89f6ca0e4b7f8eaba720200d7cda","parentId":"wrk_1ab8149399c840b69bb18c2b0d8ebd99","modified":1729089313634,"created":1729089313634,"name":"Default Jar","cookies":[],"_type":"cookie_jar"},{"_id":"spc_7c023cd55b20419fb948dbfe3956a7f0","parentId":"wrk_1ab8149399c840b69bb18c2b0d8ebd99","modified":1729089313647,"created":1729089313635,"fileName":"ManagementProductsAndUsers","contents":"","contentType":"yaml","_type":"api_spec"}]}